andy/__main__.py
andy/schema.py
andy/suite.py
andy_fraud-1.0.1.dist-info/LICENSE
andy_fraud-1.0.1.dist-info/METADATA
andy_fraud-1.0.1.dist-info/WHEEL
andy_fraud-1.0.1.dist-info/top_level.txt
andy_fraud-1.0.1.dist-info/RECORD
