Metadata-Version: 2.1
Name: andy-fraud
Version: 1.0.1
Summary: Anti-typosquatting suite
Home-page: https://github.com/Arraying/Andy
Author: Arraying
Author-email: paul.huebner@googlemail.com
License: UNKNOWN
Project-URL: Bug Tracker, https://github.com/Arraying/Andy/issues
Platform: UNKNOWN
Classifier: Programming Language :: Python :: 3
Classifier: License :: OSI Approved :: GNU General Public License v3 or later (GPLv3+)
Classifier: Operating System :: OS Independent
Requires-Python: >=3.8
License-File: LICENSE
Requires-Dist: tldextract
Requires-Dist: jsonschema
